activate.py
activate-0.2.1.dist-info/DESCRIPTION.rst
activate-0.2.1.dist-info/METADATA
activate-0.2.1.dist-info/RECORD
activate-0.2.1.dist-info/WHEEL
activate-0.2.1.dist-info/entry_points.txt
activate-0.2.1.dist-info/metadata.json
activate-0.2.1.dist-info/top_level.txt
