Metadata-Version: 1.0
Name: activate
Version: 0.2.1
Summary: Replace libsteam_api.so with an ACTiVATED one
Home-page: https://github.com/notpushkin/activate
Author: Ale & ZeDoCaixao
Author-email: UNKNOWN
License: UNKNOWN
Platform: UNKNOWN
